algofresco/__init__.py
algofresco/dict.py
algofresco/ds.py
algofresco/graph.py
algofresco/que.py
algofresco/stack.py
algofresco/tracer.py
algofresco/tree.py
algofresco/version.py
algofresco-0.0.0.dist-info/LICENSE
algofresco-0.0.0.dist-info/METADATA
algofresco-0.0.0.dist-info/WHEEL
algofresco-0.0.0.dist-info/top_level.txt
algofresco-0.0.0.dist-info/RECORD
