Metadata-Version: 2.2
Name: algofresco
Version: 0.0.0
Summary: A library to visulize algorithms and data structures
Author: Ahmed Rakan
Author-email: ar.aldhafeeri11@gmail.com
License-File: LICENSE
Requires-Dist: networkx==3.4.2
Requires-Dist: matplotlib==3.10.1
Dynamic: author
Dynamic: author-email
Dynamic: description
Dynamic: description-content-type
Dynamic: requires-dist
Dynamic: summary
